instance_checker-0.4.3.dist-info/METADATA
instance_checker-0.4.3.dist-info/WHEEL
instance_checker-0.4.3.dist-info/entry_points.txt
instance_checker/__init__.py
instance_checker/utils.py
instance_checker-0.4.3.dist-info/RECORD
