Metadata-Version: 2.1
Name: instance_checker
Version: 0.4.3
Summary: A utility module to track and limit the number of running application instances by checking processes and lock files.
Author-Email: dkurchigin <kurchigin.dmitry@yandex.ru>
License: MIT
Classifier: Programming Language :: Python :: 3
Classifier: Programming Language :: Python
Classifier: Typing :: Typed
Classifier: Programming Language :: Python :: 3 :: Only
Classifier: Programming Language :: Python :: 3.10
Classifier: Programming Language :: Python :: 3.11
Classifier: Programming Language :: Python :: 3.12
Classifier: Programming Language :: Python :: 3.13
Project-URL: Homepage, https://gitverse.ru/dkurchigin/instance_checker
Project-URL: Documentation, https://instance-checker.dkurchigin.ru/
Project-URL: Source, https://gitverse.ru/dkurchigin/instance_checker
Requires-Python: >=3.10
Requires-Dist: psutil>=7.0.0
